{
  "args": {
    "start": "2000-01-01",
    "end": "2024-04-01",
    "ticker": "SPY",
    "train_size": 156,
    "test_size": 52,
    "step": 52,
    "embargo": 2,
    "timesteps": 50000,
    "agent": "sac",
    "seed": 1,
    "max_folds": null,
    "output": "results/wf_weekly_macro_seed1.json",
    "return_weight": 0.0,
    "macro": true,
    "selective_macro": false,
    "hard_selection": false,
    "interval": "1wk"
  },
  "folds": [
    {
      "fold": 0,
      "train_start": "2000-01-01 00:00:00",
      "train_end": "2002-12-21 00:00:00",
      "test_start": "2003-01-11 00:00:00",
      "test_end": "2004-01-03 00:00:00",
      "total_return": 0.005216409262104862,
      "sharpe_ratio": 0.544247214569922,
      "sortino_ratio": 0.49623693358191623,
      "max_drawdown": 0.022177029134863774,
      "benchmark_return": 0.2599021736175417,
      "benchmark_sharpe": 3.9798601395147206,
      "benchmark_max_drawdown": 0.08096194181877492
    },
    {
      "fold": 1,
      "train_start": "2000-12-30 00:00:00",
      "train_end": "2003-12-20 00:00:00",
      "test_start": "2004-01-10 00:00:00",
      "test_end": "2005-01-01 00:00:00",
      "total_return": 0.038351155285235874,
      "sharpe_ratio": 2.320334239797374,
      "sortino_ratio": 4.646648875585056,
      "max_drawdown": 0.0340319476991752,
      "benchmark_return": 0.0567114786131204,
      "benchmark_sharpe": 1.2432281113546824,
      "benchmark_max_drawdown": 0.07530475390713993
    },
    {
      "fold": 2,
      "train_start": "2001-12-29 00:00:00",
      "train_end": "2004-12-18 00:00:00",
      "test_start": "2005-01-08 00:00:00",
      "test_end": "2005-12-31 00:00:00",
      "total_return": 0.02649716568327349,
      "sharpe_ratio": 1.361612574395122,
      "sortino_ratio": 1.9065924824373874,
      "max_drawdown": 0.032636020958794,
      "benchmark_return": 0.10542311887158763,
      "benchmark_sharpe": 2.424233761456829,
      "benchmark_max_drawdown": 0.06625649511546004
    },
    {
      "fold": 3,
      "train_start": "2002-12-28 00:00:00",
      "train_end": "2005-12-17 00:00:00",
      "test_start": "2006-01-07 00:00:00",
      "test_end": "2006-12-30 00:00:00",
      "total_return": 0.06207755440232621,
      "sharpe_ratio": 4.845478053209739,
      "sortino_ratio": 13.559958677358653,
      "max_drawdown": 0.00997299776861415,
      "benchmark_return": 0.1123633641239789,
      "benchmark_sharpe": 2.6334942035224347,
      "benchmark_max_drawdown": 0.06379410672557753
    },
    {
      "fold": 4,
      "train_start": "2003-12-27 00:00:00",
      "train_end": "2006-12-16 00:00:00",
      "test_start": "2007-01-06 00:00:00",
      "test_end": "2007-12-29 00:00:00",
      "total_return": -0.020215182118559168,
      "sharpe_ratio": -0.612643762402,
      "sortino_ratio": -0.789596851707113,
      "max_drawdown": 0.08301804684183146,
      "benchmark_return": 0.004730759492872792,
      "benchmark_sharpe": 0.23441403646392484,
      "benchmark_max_drawdown": 0.09128147980459186
    },
    {
      "fold": 5,
      "train_start": "2004-12-25 00:00:00",
      "train_end": "2007-12-15 00:00:00",
      "test_start": "2008-01-05 00:00:00",
      "test_end": "2008-12-27 00:00:00",
      "total_return": 0.09166831436340363,
      "sharpe_ratio": 1.8771774753766584,
      "sortino_ratio": 3.5535542115322243,
      "max_drawdown": 0.11541047641500395,
      "benchmark_return": -0.3207456397029693,
      "benchmark_sharpe": -2.0302554494530187,
      "benchmark_max_drawdown": 0.4365602515117352
    },
    {
      "fold": 6,
      "train_start": "2005-12-24 00:00:00",
      "train_end": "2008-12-13 00:00:00",
      "test_start": "2009-01-03 00:00:00",
      "test_end": "2009-12-26 00:00:00",
      "total_return": 0.024155299898413213,
      "sharpe_ratio": 1.60261041883403,
      "sortino_ratio": 2.2131732991840103,
      "max_drawdown": 0.028932960012671177,
      "benchmark_return": 0.2798275681770728,
      "benchmark_sharpe": 2.503891188579571,
      "benchmark_max_drawdown": 0.226400262029669
    },
    {
      "fold": 7,
      "train_start": "2006-12-23 00:00:00",
      "train_end": "2009-12-12 00:00:00",
      "test_start": "2010-01-02 00:00:00",
      "test_end": "2010-12-25 00:00:00",
      "total_return": -0.1636072786397663,
      "sharpe_ratio": -6.609921190748131,
      "sortino_ratio": -6.413280390122356,
      "max_drawdown": 0.18623036192232,
      "benchmark_return": 0.11912902379451258,
      "benchmark_sharpe": 1.6559665337125522,
      "benchmark_max_drawdown": 0.15699695321597992
    },
    {
      "fold": 8,
      "train_start": "2007-12-22 00:00:00",
      "train_end": "2010-12-11 00:00:00",
      "test_start": "2011-01-01 00:00:00",
      "test_end": "2011-12-24 00:00:00",
      "total_return": -0.04579924854291996,
      "sharpe_ratio": -1.0702840954183375,
      "sortino_ratio": -1.1981446538053244,
      "max_drawdown": 0.11147667006131252,
      "benchmark_return": 0.007810002668015776,
      "benchmark_sharpe": 0.3183107499953822,
      "benchmark_max_drawdown": 0.17028199273278338
    },
    {
      "fold": 9,
      "train_start": "2008-12-20 00:00:00",
      "train_end": "2011-12-10 00:00:00",
      "test_start": "2011-12-31 00:00:00",
      "test_end": "2012-12-22 00:00:00",
      "total_return": -0.046308182293405845,
      "sharpe_ratio": -2.559006151934067,
      "sortino_ratio": -2.975279348129711,
      "max_drawdown": 0.07522406284870085,
      "benchmark_return": 0.12078223782048382,
      "benchmark_sharpe": 2.3633763591043975,
      "benchmark_max_drawdown": 0.08983693249249537
    },
    {
      "fold": 10,
      "train_start": "2009-12-19 00:00:00",
      "train_end": "2012-12-08 00:00:00",
      "test_start": "2012-12-29 00:00:00",
      "test_end": "2013-12-21 00:00:00",
      "total_return": 0.04345546676472994,
      "sharpe_ratio": 3.023128740425157,
      "sortino_ratio": 3.3440892644526987,
      "max_drawdown": 0.02467580917631567,
      "benchmark_return": 0.28142717951279544,
      "benchmark_sharpe": 6.266454006562526,
      "benchmark_max_drawdown": 0.04714282122260151
    },
    {
      "fold": 11,
      "train_start": "2010-12-18 00:00:00",
      "train_end": "2013-12-07 00:00:00",
      "test_start": "2013-12-28 00:00:00",
      "test_end": "2014-12-20 00:00:00",
      "total_return": 0.0357550308457097,
      "sharpe_ratio": 1.6920193781587016,
      "sortino_ratio": 2.3623231067594186,
      "max_drawdown": 0.05119218514885962,
      "benchmark_return": 0.16197119444785113,
      "benchmark_sharpe": 3.2282222739555766,
      "benchmark_max_drawdown": 0.058470520812007154
    },
    {
      "fold": 12,
      "train_start": "2011-12-17 00:00:00",
      "train_end": "2014-12-06 00:00:00",
      "test_start": "2014-12-27 00:00:00",
      "test_end": "2015-12-19 00:00:00",
      "total_return": -0.10591787059782408,
      "sharpe_ratio": -3.8674385883260065,
      "sortino_ratio": -4.696453599932954,
      "max_drawdown": 0.13602774239139243,
      "benchmark_return": 0.02187767477290749,
      "benchmark_sharpe": 0.5099283985185733,
      "benchmark_max_drawdown": 0.09360914658034195
    },
    {
      "fold": 13,
      "train_start": "2012-12-15 00:00:00",
      "train_end": "2015-12-05 00:00:00",
      "test_start": "2015-12-26 00:00:00",
      "test_end": "2016-12-17 00:00:00",
      "total_return": 0.040519872091487635,
      "sharpe_ratio": 2.411603254656121,
      "sortino_ratio": 4.1089320782332,
      "max_drawdown": 0.0318583929427905,
      "benchmark_return": 0.13090157923870002,
      "benchmark_sharpe": 2.387946404083096,
      "benchmark_max_drawdown": 0.08456382566397702
    },
    {
      "fold": 14,
      "train_start": "2013-12-14 00:00:00",
      "train_end": "2016-12-03 00:00:00",
      "test_start": "2016-12-24 00:00:00",
      "test_end": "2017-12-16 00:00:00",
      "total_return": 0.07455082047883668,
      "sharpe_ratio": 6.526972617878841,
      "sortino_ratio": 10.585423026632212,
      "max_drawdown": 0.019721574979284843,
      "benchmark_return": 0.22001835879344303,
      "benchmark_sharpe": 8.593201927081019,
      "benchmark_max_drawdown": 0.0205453477220323
    },
    {
      "fold": 15,
      "train_start": "2014-12-13 00:00:00",
      "train_end": "2017-12-02 00:00:00",
      "test_start": "2017-12-23 00:00:00",
      "test_end": "2018-12-15 00:00:00",
      "total_return": -0.02325415361687221,
      "sharpe_ratio": -0.9718925884950499,
      "sortino_ratio": -0.9096761924943036,
      "max_drawdown": 0.07806598087106169,
      "benchmark_return": -0.08623205550620464,
      "benchmark_sharpe": -0.9204159495506044,
      "benchmark_max_drawdown": 0.17205553260578713
    },
    {
      "fold": 16,
      "train_start": "2015-12-12 00:00:00",
      "train_end": "2018-12-01 00:00:00",
      "test_start": "2018-12-22 00:00:00",
      "test_end": "2019-12-14 00:00:00",
      "total_return": 0.11188154067020557,
      "sharpe_ratio": 5.28254325932153,
      "sortino_ratio": 12.879939593168732,
      "max_drawdown": 0.02996256610237296,
      "benchmark_return": 0.3126318902052711,
      "benchmark_sharpe": 5.875118920725058,
      "benchmark_max_drawdown": 0.06380304361747208
    },
    {
      "fold": 17,
      "train_start": "2016-12-10 00:00:00",
      "train_end": "2019-11-30 00:00:00",
      "test_start": "2019-12-21 00:00:00",
      "test_end": "2020-12-12 00:00:00",
      "total_return": 0.07581936019205648,
      "sharpe_ratio": 2.6779338028969497,
      "sortino_ratio": 9.52487656692141,
      "max_drawdown": 0.044697174114442906,
      "benchmark_return": 0.159878012957891,
      "benchmark_sharpe": 1.3996938204755993,
      "benchmark_max_drawdown": 0.32227484635705655
    },
    {
      "fold": 18,
      "train_start": "2017-12-09 00:00:00",
      "train_end": "2020-11-28 00:00:00",
      "test_start": "2020-12-19 00:00:00",
      "test_end": "2021-12-11 00:00:00",
      "total_return": -0.006406924445205368,
      "sharpe_ratio": -0.594642190743178,
      "sortino_ratio": -0.8796492161368303,
      "max_drawdown": 0.026624071108694188,
      "benchmark_return": 0.2584509868216781,
      "benchmark_sharpe": 4.356029686832754,
      "benchmark_max_drawdown": 0.03851143535787407
    },
    {
      "fold": 19,
      "train_start": "2018-12-08 00:00:00",
      "train_end": "2021-11-27 00:00:00",
      "test_start": "2021-12-18 00:00:00",
      "test_end": "2022-12-10 00:00:00",
      "total_return": -0.056970456246479444,
      "sharpe_ratio": -0.7619483894069924,
      "sortino_ratio": -1.1008894280075012,
      "max_drawdown": 0.14573193800365897,
      "benchmark_return": -0.17614192791415703,
      "benchmark_sharpe": -1.604096510042676,
      "benchmark_max_drawdown": 0.23927197586166887
    },
    {
      "fold": 20,
      "train_start": "2019-12-07 00:00:00",
      "train_end": "2022-11-26 00:00:00",
      "test_start": "2022-12-17 00:00:00",
      "test_end": "2023-12-09 00:00:00",
      "total_return": -0.026343903299576924,
      "sharpe_ratio": -1.405362931304312,
      "sortino_ratio": -1.8229905014680483,
      "max_drawdown": 0.06607339807074718,
      "benchmark_return": 0.2392969600530747,
      "benchmark_sharpe": 3.792716503111573,
      "benchmark_max_drawdown": 0.09802905755056804
    }
  ],
  "aggregate": {
    "total_return": {
      "mean": 0.006434513816055903,
      "std": 0.0670676627551364,
      "median": 0.024155299898413213,
      "min": -0.1636072786397663,
      "max": 0.11188154067020557,
      "n": 21
    },
    "sharpe_ratio": {
      "mean": 0.7482152924162891,
      "std": 3.0936702948714765,
      "median": 1.361612574395122,
      "min": -6.609921190748131,
      "max": 6.526972617878841,
      "n": 21
    },
    "sortino_ratio": {
      "mean": 2.3045613301925134,
      "std": 5.467580845055856,
      "median": 1.9065924824373874,
      "min": -6.413280390122356,
      "max": 13.559958677358653,
      "n": 21
    },
    "max_drawdown": {
      "mean": 0.06446387650347181,
      "std": 0.04888890169887005,
      "median": 0.044697174114442906,
      "min": 0.00997299776861415,
      "max": 0.18623036192232,
      "n": 21
    },
    "benchmark_return": {
      "mean": 0.10809590194568894,
      "std": 0.16069377723551306,
      "median": 0.12078223782048382,
      "min": -0.3207456397029693,
      "max": 0.3126318902052711,
      "n": 21
    },
    "benchmark_sharpe": {
      "mean": 2.3433961483811414,
      "std": 2.6124929641744843,
      "median": 2.387946404083096,
      "min": -2.0302554494530187,
      "max": 8.593201927081019,
      "n": 21
    }
  },
  "excess_return": {
    "mean": -0.101661388129633,
    "std": 0.16251227366300797,
    "median": -0.12621616360214144,
    "min": -0.2827363024342789,
    "max": 0.41241395406637293,
    "n": 21
  },
  "excess_sharpe": {
    "mean": -1.5951808559648522,
    "std": 2.89280272032127,
    "median": -1.0626211870617068,
    "min": -8.265887724460683,
    "max": 3.907432924829677,
    "n": 21
  },
  "fold_win_rate": 0.14285714285714285
}